AUTHORS.rst
CONTRIBUTING.rst
HISTORY.rst
LICENSE
MANIFEST.in
README.rst
setup.cfg
setup.py
xmldataset/__init__.py
xmldataset/__main__.py
xmldataset.egg-info/PKG-INFO
xmldataset.egg-info/SOURCES.txt
xmldataset.egg-info/dependency_links.txt
xmldataset.egg-info/not-zip-safe
xmldataset.egg-info/top_level.txt