Metadata-Version: 1.1
Name: xmldataset
Version: 1.0.1
Summary: XML Dataset: xml parsing made easy
Home-page: https://github.com/spurin/xmldataset
Author: James Spurin
Author-email: james@spurin.com
License: BSD
Keywords: xmldataset
Platform: UNKNOWN
Classifier: Development Status :: 5 - Production/Stable
Classifier: Intended Audience :: Developers
Classifier: License :: OSI Approved :: BSD License
Classifier: Natural Language :: English
Classifier: Programming Language :: Python :: 2
Classifier: Programming Language :: Python :: 3
